sketch_document_py/__init__.py
sketch_document_py/sketch_file/__init__.py
sketch_document_py/sketch_file/file.py
sketch_document_py/sketch_file_format/__init__.py
sketch_document_py/sketch_file_format/types.py
sketch_document_py-1.0.4.dist-info/LICENSE
sketch_document_py-1.0.4.dist-info/WHEEL
sketch_document_py-1.0.4.dist-info/METADATA
sketch_document_py-1.0.4.dist-info/RECORD
