Metadata-Version: 2.1
Name: sketch-document-py
Version: 1.0.4
Summary: This project contains the APIs to work with Sketch documents and document elements in Python dataclass.
Home-page: https://github.com/Borealin/sketch-document-py
License: MIT
Author: Borealin
Author-email: shichuning@gmail.com
Requires-Python: >=3.9,<4.0
Classifier: License :: OSI Approved :: MIT License
Classifier: Programming Language :: Python :: 3
Classifier: Programming Language :: Python :: 3.10
Classifier: Programming Language :: Python :: 3.9
Requires-Dist: fastclasses-json (>=0.5.0,<0.6.0)
Project-URL: Repository, https://github.com/Borealin/sketch-document-py
